{
  "tenantId": "pb",
  "moduleName": "ACCESSCONTROL-ROLEACTIONS",
  "roleactions": [
    {
      "rolecode": "SYS_INTEGRATOR_WATER_SEW",
      "actionid": 207,
      "actioncode": "",
      "tenantId": "pb"
    },
    {
      "rolecode": "SYS_INTEGRATOR_WATER_SEW",
      "actionid": 570,
      "actioncode": "",
      "tenantId": "pb"
    },
    {
      "rolecode": "SYS_INTEGRATOR_WATER_SEW",
      "actionid": 604,
      "actioncode": "",
      "tenantId": "pb"
    },
    {
      "rolecode": "SYS_INTEGRATOR_WATER_SEW",
      "actionid": 696,
      "actioncode": "",
      "tenantId": "pb"
    },
    {
      "rolecode": "SYS_INTEGRATOR_WATER_SEW",
      "actionid": 926,
      "actioncode": "",
      "tenantId": "pb"
    },
    {
      "rolecode": "SYS_INTEGRATOR_WATER_SEW",
      "actionid": 1534,
      "actioncode": "",
      "tenantId": "pb"
    },
    {
      "rolecode": "SYS_INTEGRATOR_WATER_SEW",
      "actionid": 1601,
      "actioncode": "",
      "tenantId": "pb"
    },
    {
      "rolecode": "SYS_INTEGRATOR_WATER_SEW",
      "actionid": 1676,
      "actioncode": "",
      "tenantId": "pb"
    },
    {
      "rolecode": "SYS_INTEGRATOR_WATER_SEW",
      "actionid": 1689,
      "actioncode": "",
      "tenantId": "pb"
    },
    {
      "rolecode": "WS_CITIZEN",
      "actionid": 870,
      "actioncode": "",
      "tenantId": "pb"
    },
     {
      "rolecode": "CITIZEN",
      "actionid": 1913,
      "actioncode": "",
      "tenantId": "pb"
    }
  ]
}
